MANIFEST.in
README.rst
setup.py
carson/__init__.py
carson/admin.py
carson/json_field.py
carson/managers.py
carson/models.py
carson/streamer.py
carson/tests.py
carson/urls.py
carson/utils.py
carson/views.py
carson/management/__init__.py
carson/management/commands/__init__.py
carson/management/commands/get_tweets.py
carson/management/commands/lookup_twitter_ids.py
carson/migrations/0001_initial.py
carson/migrations/0002_add_timestamp.py
carson/migrations/0003_add_status_id.py
carson/migrations/0004_add_index_to_status_id.py
carson/migrations/0005_add_index_to_timestamp.py
carson/migrations/__init__.py
django_carson.egg-info/PKG-INFO
django_carson.egg-info/SOURCES.txt
django_carson.egg-info/dependency_links.txt
django_carson.egg-info/requires.txt
django_carson.egg-info/top_level.txt