Metadata-Version: 1.0
Name: django-carson
Version: 0.2
Summary: Easily store and display tweets from a set of users or tweets about a given topic
Home-page: https://github.com/edavis/django-carson
Author: Eric Davis
Author-email: ed@npri.org
License: UNKNOWN
Platform: UNKNOWN
Classifier: Development Status :: 4 - Beta
Classifier: Framework :: Django
Classifier: Intended Audience :: Developers
Classifier: License :: OSI Approved :: BSD License
Classifier: Natural Language :: English
Classifier: Operating System :: OS Independent
Classifier: Programming Language :: Python
Classifier: Topic :: Internet
